[
  {
    "score":25,
    "pubdate":"2025-07-13-07-16-33 +0000",
    "source":"nyt",
    "title":"For Families of Air India Crash Victims, Report Brings No Closure",
    "link":"https:\/\/www.nytimes.com\/2025\/07\/13\/world\/asia\/air-india-crash-report-victim-families.html"
  },
  {
    "score":24,
    "pubdate":"2025-07-12-17-01-00 +0000",
    "source":"wsj",
    "title":"The U.S. will charge a 30% tariff on the European Union and Mexico effective Aug. 1, President Trump said in letters to the leaders of each trading partner, posted on Truth Social",
    "link":"https:\/\/www.wsj.com\/economy\/trade\/trump-threatens-30-tariffs-on-eu-mexico-c48ce36f"
  },
  {
    "score":23,
    "pubdate":"2025-07-13-01-00-00 +0000",
    "source":"wsj",
    "title":"Economists expect stronger growth and job creation, lower risk of recession and cooler inflation than they did three months ago, according to a Wall Street Journal survey",
    "link":"https:\/\/www.wsj.com\/economy\/economists-see-lower-recession-risk-and-stronger-job-growth-wsj-survey-10d6e476"
  },
  {
    "score":19,
    "pubdate":"2025-07-12-21-11-05 +0000",
    "source":"bbc",
    "title":"The mushroom killer was obsessed with true crime. Now true crime fans are obsessed with her",
    "link":"https:\/\/www.bbc.com\/news\/articles\/c0m8glx2zleo"
  },
  {
    "score":13,
    "pubdate":"2025-07-13-01-04-00 +0000",
    "source":"wsj",
    "title":"Answers to frequently asked questions about The Wall Street Journal's Economic Forecasting survey plus links to stories and archival data.",
    "link":"https:\/\/www.wsj.com\/economy\/economic-forecasting-survey-archive-11617814998"
  },
  {
    "score":13,
    "pubdate":"2025-07-12-14-00-00 +0000",
    "source":"wsj",
    "title":"The White House has an explanation for the nearly $2 trillion of manufacturing-related projects announced since the start of the year. It\u2019s the Trump Effect.",
    "link":"https:\/\/www.wsj.com\/politics\/policy\/trump-new-us-factories-d2981280"
  },
  {
    "score":11,
    "pubdate":"2025-07-12-09-30-00 +0000",
    "source":"wsj",
    "title":"Pittsburgh is striving to turn its old steel mills into a high-tech center to help reverse economic decline",
    "link":"https:\/\/www.wsj.com\/tech\/ai\/can-pittsburghs-old-steel-mills-be-turned-into-an-ai-hub-bb2dd8ff"
  },
  {
    "score":10,
    "pubdate":"2025-07-13-00-00-42 +0000",
    "source":"bbc",
    "title":"Putin's friend Gergiev set to conduct as Italy breaks ban on pro-Kremlin artists",
    "link":"https:\/\/www.bbc.com\/news\/articles\/czxw4n7vy70o"
  },
  {
    "score":10,
    "pubdate":"2025-07-12-21-49-47 +0000",
    "source":"bbc",
    "title":"Gaza hospital says 24 people killed near aid site as witnesses blame IDF",
    "link":"https:\/\/www.bbc.com\/news\/articles\/cp90v2ng70yo"
  },
  {
    "score":10,
    "pubdate":"2025-07-12-14-34-23 +0000",
    "source":"bbc",
    "title":"Israeli settlers kill Palestinians in West Bank attack, health ministry says",
    "link":"https:\/\/www.bbc.com\/news\/articles\/cm2mknzn99eo"
  }
]