{
  "entries": [
    {
      "title": "British man is only passenger to survive India plane crash",
      "link": "https://www.bbc.com/news/articles/ce3v6drp96zo",
      "published": "Thu, 12 Jun 2025 21:29:13 GMT",
      "sentiment": -0.05
    },
    {
      "title": "Who are the victims of the Air India plane crash?",
      "link": "https://www.bbc.com/news/articles/cdd28legnzvo",
      "published": "Thu, 12 Jun 2025 22:07:12 GMT",
      "sentiment": 0.25
    },
    {
      "title": "Air India plane crash - how the day unfolded",
      "link": "https://www.bbc.com/news/videos/cx2q3z716v9o",
      "published": "Thu, 12 Jun 2025 20:29:52 GMT",
      "sentiment": 0.0
    },
    {
      "title": "BTS fan attempts to break into band member's home",
      "link": "https://www.bbc.com/news/articles/czdy60gd02eo",
      "published": "Thu, 12 Jun 2025 03:57:32 GMT",
      "sentiment": -0.19999999999999998
    },
    {
      "title": "Taiwan jails China captain for undersea cable sabotage in landmark case",
      "link": "https://www.bbc.com/news/articles/cwy3zy9jvd4o",
      "published": "Thu, 12 Jun 2025 07:01:54 GMT",
      "sentiment": -0.05
    },
    {
      "title": "US reviewing Aukus submarine pact as part of 'America First' agenda",
      "link": "https://www.bbc.com/news/articles/cy8d3d5l9l1o",
      "published": "Thu, 12 Jun 2025 01:43:24 GMT",
      "sentiment": 0.049999999999999996
    },
    {
      "title": "Officials race to tow burning ship away from India coast to prevent 'ecological disaster'",
      "link": "https://www.bbc.com/news/articles/cy4kxdxjz1yo",
      "published": "Thu, 12 Jun 2025 06:05:19 GMT",
      "sentiment": 0.16666666666666666
    },
    {
      "title": "Pope names Chinese bishop as he keeps historic Vatican-Beijing accord",
      "link": "https://www.bbc.com/news/articles/cn4g9dlnynmo",
      "published": "Thu, 12 Jun 2025 14:27:52 GMT",
      "sentiment": 0.0
    },
    {
      "title": "Trump says rare earths deal 'done' with China",
      "link": "https://www.bbc.com/news/articles/c4gkmy26e2po",
      "published": "Thu, 12 Jun 2025 01:38:40 GMT",
      "sentiment": 0.3
    },
    {
      "title": "What is Aukus, the submarine deal between Australia, the UK and US?",
      "link": "https://www.bbc.com/news/articles/cgr589k5yleo",
      "published": "Thu, 12 Jun 2025 06:03:55 GMT",
      "sentiment": -0.1
    },
    {
      "title": "South Korea turns off propaganda loudspeakers to North",
      "link": "https://www.bbc.com/news/articles/c4g65nrek75o",
      "published": "Wed, 11 Jun 2025 09:13:04 GMT",
      "sentiment": 0.018181818181818174
    },
    {
      "title": "Four crew members missing as Singapore-flagged cargo ship burns off India coast",
      "link": "https://www.bbc.com/news/articles/cd7g9el8q15o",
      "published": "Tue, 10 Jun 2025 07:03:18 GMT",
      "sentiment": -0.2
    },
    {
      "title": "South Korea cements cultural status with six Tonys for Maybe Happy Ending",
      "link": "https://www.bbc.com/news/articles/cy0j71xgrv8o",
      "published": "Mon, 09 Jun 2025 05:56:09 GMT",
      "sentiment": 0.42000000000000004
    },
    {
      "title": "Missing Indian bride arrested for allegedly murdering husband on honeymoon",
      "link": "https://www.bbc.com/news/articles/ckgn50p90epo",
      "published": "Mon, 09 Jun 2025 11:03:08 GMT",
      "sentiment": -0.16666666666666666
    },
    {
      "title": "What could have caused Air India plane to crash in 30 seconds?",
      "link": "https://www.bbc.com/news/articles/c626y121rxxo",
      "published": "Thu, 12 Jun 2025 20:20:47 GMT",
      "sentiment": -0.15833333333333335
    },
    {
      "title": "What we know so far after Air India flight to London crashes in Ahmedabad",
      "link": "https://www.bbc.com/news/articles/c5y5nq170z4o",
      "published": "Thu, 12 Jun 2025 17:26:05 GMT",
      "sentiment": 0.05
    },
    {
      "title": "Who are the victims of the Air India plane crash?",
      "link": "https://www.bbc.com/news/articles/cdd28legnzvo",
      "published": "Thu, 12 Jun 2025 22:07:12 GMT",
      "sentiment": 0.25
    },
    {
      "title": "Gangster tells BBC why India's biggest hip-hop star was murdered",
      "link": "https://www.bbc.com/news/articles/c87j5v4xjxqo",
      "published": "Wed, 11 Jun 2025 05:23:51 GMT",
      "sentiment": 0.0
    },
    {
      "title": "'Scary and stressful': Indian students reconsider plans for US education",
      "link": "https://www.bbc.com/news/articles/c8re8vy4g14o",
      "published": "Mon, 09 Jun 2025 22:31:19 GMT",
      "sentiment": -0.16666666666666666
    },
    {
      "title": "China's electric cars are becoming slicker and cheaper - but is there a deeper cost?",
      "link": "https://www.bbc.com/news/articles/cy8d4v69jw6o",
      "published": "Mon, 09 Jun 2025 23:04:10 GMT",
      "sentiment": 0.15
    }
  ]
}