{
  "entries": [
    {
      "title": "Supreme Court Won’t Revive Aggressive Florida Immigration Law",
      "link": "https://www.nytimes.com/2025/07/09/us/politics/supreme-court-florida-immigration-law.html",
      "published": "Wed, 09 Jul 2025 19:48:05 +0000",
      "sentiment": 0.0
    },
    {
      "title": "Administration Takes Steps to Target 2 Officials Who Investigated Trump",
      "link": "https://www.nytimes.com/2025/07/09/us/politics/ratcliffe-brennan-cia.html",
      "published": "Wed, 09 Jul 2025 19:13:09 +0000",
      "sentiment": 0.25
    },
    {
      "title": "Senate Confirms Bryan Bedford to Lead FAA",
      "link": "https://www.nytimes.com/2025/07/09/us/politics/bedford-faa-senate-confirmation.html",
      "published": "Wed, 09 Jul 2025 18:49:10 +0000",
      "sentiment": -0.20000000000000004
    },
    {
      "title": "Thune Says Russia Sanctions Vote Could Come as Soon as This Month",
      "link": "https://www.nytimes.com/2025/07/09/us/politics/russia-sanctions-senate-thune-trump.html",
      "published": "Wed, 09 Jul 2025 18:38:25 +0000",
      "sentiment": 0.0
    },
    {
      "title": "Biden’s Former Doctor, Kevin O’Connor, Refuses Questions in GOP Health Inquiry",
      "link": "https://www.nytimes.com/2025/07/09/us/politics/kevin-oconnor-biden-doctor.html",
      "published": "Wed, 09 Jul 2025 17:18:06 +0000",
      "sentiment": 0.14285714285714285
    },
    {
      "title": "Trump Administration Renews Attacks On Harvard With Negotiations Uncertain",
      "link": "https://www.nytimes.com/2025/07/09/us/politics/trump-harvard-data-accreditation.html",
      "published": "Wed, 09 Jul 2025 17:16:33 +0000",
      "sentiment": 0.0
    },
    {
      "title": "A Dark-of-Night Flood Escape at the River Inn in Texas",
      "link": "https://www.nytimes.com/2025/07/09/us/texas-floods-river-inn.html",
      "published": "Wed, 09 Jul 2025 19:24:43 +0000",
      "sentiment": 0.3333333333333333
    },
    {
      "title": "Trump Administration Sues California Over Transgender Athletes",
      "link": "https://www.nytimes.com/2025/07/09/us/politics/trump-administration-sues-california-over-transgender-athletes.html",
      "published": "Wed, 09 Jul 2025 16:41:17 +0000",
      "sentiment": 0.0
    },
    {
      "title": "EU Seeks U.S. Trade Deal as Trump Tariff Threat Looms",
      "link": "https://www.nytimes.com/2025/07/09/us/politics/eu-trade-deal-trump-tariffs.html",
      "published": "Wed, 09 Jul 2025 16:21:58 +0000",
      "sentiment": -0.05
    },
    {
      "title": "Elon Musk Consulted Curtis Yarvin, Right-Wing Thinker, on Third Party",
      "link": "https://www.nytimes.com/2025/07/09/us/politics/elon-musk-curtis-yarvin-third-party.html",
      "published": "Wed, 09 Jul 2025 16:41:52 +0000",
      "sentiment": 0.0
    },
    {
      "title": "Trump to Discuss Economic Investment With African Leaders at White House Meeting",
      "link": "https://www.nytimes.com/2025/07/09/us/politics/trump-african-leaders-china.html",
      "published": "Wed, 09 Jul 2025 16:01:38 +0000",
      "sentiment": 0.05
    },
    {
      "title": "U.S. Copper Prices Surge on Trump’s Threat of 50% Tariff",
      "link": "https://www.nytimes.com/2025/07/09/us/politics/trump-copper-tariffs.html",
      "published": "Wed, 09 Jul 2025 15:17:52 +0000",
      "sentiment": 0.30333333333333334
    },
    {
      "title": "Did the Texas Flood Warnings Come in Time?",
      "link": "https://www.nytimes.com/video/us/100000010273289/tracking-texas-flood-warning-system.html",
      "published": "Wed, 09 Jul 2025 13:37:00 +0000",
      "sentiment": -0.03181818181818183
    },
    {
      "title": "Death Toll Reaches at Least 119 in Texas Floods, With 173 Missing",
      "link": "https://www.nytimes.com/2025/07/09/us/texas-floods-missing-search.html",
      "published": "Wed, 09 Jul 2025 18:49:29 +0000",
      "sentiment": -0.25
    },
    {
      "title": "Bessent Steps Up Criticism of Fed as Auditions for Chair Intensify",
      "link": "https://www.nytimes.com/2025/07/09/us/politics/bessent-federal-reserve-chair.html",
      "published": "Wed, 09 Jul 2025 16:46:44 +0000",
      "sentiment": 0.0
    },
    {
      "title": "Texas Flooding Shows the Dangers Posed by Hill Country Rivers",
      "link": "https://www.nytimes.com/2025/07/09/us/texas-hill-country-rivers-floods.html",
      "published": "Wed, 09 Jul 2025 09:01:40 +0000",
      "sentiment": 0.35
    },
    {
      "title": "Trump Treats Tariffs More as a Form of Power Than as a Trade Tool",
      "link": "https://www.nytimes.com/2025/07/09/us/politics/trump-tariffs-trade-policy.html",
      "published": "Wed, 09 Jul 2025 13:17:51 +0000",
      "sentiment": 0.5
    },
    {
      "title": "How Crypto Lobbying Won Over Trump",
      "link": "https://www.nytimes.com/2025/07/09/us/politics/trump-crypto-lobbying.html",
      "published": "Wed, 09 Jul 2025 12:45:19 +0000",
      "sentiment": 0.4
    },
    {
      "title": "Trump Takes Reins on U.S. Economy With Policy Bill and Tariffs Renewal",
      "link": "https://www.nytimes.com/2025/07/09/us/politics/trump-bill-tariffs-economy.html",
      "published": "Wed, 09 Jul 2025 10:54:34 +0000",
      "sentiment": 0.2
    },
    {
      "title": "Trump Got the Green Light to Fire Federal Workers. Now, They Wait.",
      "link": "https://www.nytimes.com/2025/07/08/us/politics/trump-federal-workers-firings.html",
      "published": "Wed, 09 Jul 2025 13:35:11 +0000",
      "sentiment": 0.07500000000000001
    },
    {
      "title": "L.A. Moves to Join Lawsuit Against Trump Administration’s Immigration Raids",
      "link": "https://www.nytimes.com/2025/07/08/us/politics/la-immigration-raids-trump-lawsuit.html",
      "published": "Wed, 09 Jul 2025 01:39:53 +0000",
      "sentiment": 0.26666666666666666
    },
    {
      "title": "More Storms Are Expected in New Mexico, After Flooding Killed 3",
      "link": "https://www.nytimes.com/2025/07/08/us/flooding-ruidoso-new-mexico.html",
      "published": "Wed, 09 Jul 2025 19:29:35 +0000",
      "sentiment": 0.06727272727272728
    },
    {
      "title": "Abbott Calls Seeking Blame for Floods ‘the Word Choice of Losers’",
      "link": "https://www.nytimes.com/2025/07/08/us/abbott-blame-floods-losers-football.html",
      "published": "Tue, 08 Jul 2025 23:51:10 +0000",
      "sentiment": -0.2
    },
    {
      "title": "Search-and-rescue teams from other states pour into Central Texas.",
      "link": "https://www.nytimes.com/live/2025/07/08/us/texas-floods/search-and-rescue-teams-from-other-states-pour-into-central-texas",
      "published": "Tue, 08 Jul 2025 23:37:33 +0000",
      "sentiment": -0.0625
    },
    {
      "title": "Trump’s Frustration With Putin Preceded Resumption of U.S. Weapons to Ukraine",
      "link": "https://www.nytimes.com/2025/07/08/us/politics/trump-putin-ukraine.html",
      "published": "Wed, 09 Jul 2025 00:51:12 +0000",
      "sentiment": 0.0
    },
    {
      "title": "Trash Overflows in Philadelphia as City Workers’ Strike Enters Second Week",
      "link": "https://www.nytimes.com/2025/07/08/us/trash-philadelphia-strike.html",
      "published": "Wed, 09 Jul 2025 13:28:01 +0000",
      "sentiment": 0.16666666666666666
    },
    {
      "title": "Trump Uses Cabinet Meeting to Vent About Epstein, Putin and Powell",
      "link": "https://www.nytimes.com/2025/07/08/us/politics/trump-cabinet-meeting-decor.html",
      "published": "Tue, 08 Jul 2025 23:18:04 +0000",
      "sentiment": 0.1
    },
    {
      "title": "Trump and Bondi, Confronted Over Epstein Files, Tell Supporters to Move On",
      "link": "https://www.nytimes.com/2025/07/08/us/politics/trump-epstein.html",
      "published": "Wed, 09 Jul 2025 03:29:19 +0000",
      "sentiment": 0.07500000000000001
    },
    {
      "title": "What Is a Trade Deal? Trump Takes an Expansive View.",
      "link": "https://www.nytimes.com/2025/07/08/us/politics/trump-trade-deal.html",
      "published": "Wed, 09 Jul 2025 02:28:13 +0000",
      "sentiment": -0.09285714285714286
    },
    {
      "title": "Supreme Court Clears Way for Trump Administration’s Mass Firings of Federal Workers",
      "link": "https://www.nytimes.com/2025/07/08/us/politics/supreme-court-federal-workers-layoffs.html",
      "published": "Tue, 08 Jul 2025 22:05:38 +0000",
      "sentiment": 0.0
    }
  ]
}