{
  "entries": [
    {
      "title": "Trump Threatens Steep Tariffs on Goods From E.U. and Mexico",
      "link": "https://www.nytimes.com/2025/07/12/us/politics/europe-eu-tariffs-trade.html",
      "published": "Sat, 12 Jul 2025 16:44:29 +0000",
      "sentiment": 0.25
    },
    {
      "title": "A Mother of Five Survived the Flood to Return to a Cabin in Ruins",
      "link": "https://www.nytimes.com/2025/07/12/us/politics/texas-flood-survivor-damage.html",
      "published": "Sat, 12 Jul 2025 14:36:27 +0000",
      "sentiment": -0.075
    },
    {
      "title": "Trump’s Birthright Citizenship Ban Faces New Peril: Class Actions",
      "link": "https://www.nytimes.com/2025/07/12/us/politics/birthright-citizenship-class-action.html",
      "published": "Sat, 12 Jul 2025 09:01:16 +0000",
      "sentiment": 0.04545454545454545
    },
    {
      "title": "After Texas Disaster, Trump Shifts His Tone on FEMA",
      "link": "https://www.nytimes.com/2025/07/11/us/politics/trump-fema-texas-flood.html",
      "published": "Sat, 12 Jul 2025 03:49:01 +0000",
      "sentiment": 0.05
    },
    {
      "title": "Aware of Trump's Desire for Retribution, Experts Appear Shy to Speak Up",
      "link": "https://www.nytimes.com/2025/07/11/us/politics/trump-retribution.html",
      "published": "Fri, 11 Jul 2025 23:21:41 +0000",
      "sentiment": 0.057272727272727274
    },
    {
      "title": "Schumer Urges RFK Jr. to Declare Public Health Emergency Over Measles",
      "link": "https://www.nytimes.com/2025/07/11/us/politics/measles-public-health-emergency-rfk-jr.html",
      "published": "Fri, 11 Jul 2025 21:49:42 +0000",
      "sentiment": -0.0625
    },
    {
      "title": "David Gergen, Adviser to Presidents and Political Commentator, Dies at 83",
      "link": "https://www.nytimes.com/2025/07/11/us/politics/david-gergen-dead.html",
      "published": "Sat, 12 Jul 2025 05:15:42 +0000",
      "sentiment": 0.20249999999999999
    },
    {
      "title": "Immigration Arrests in Los Angeles Spike Amid Aggressive Enforcement",
      "link": "https://www.nytimes.com/2025/07/11/us/politics/los-angeles-immigration-enforcement.html",
      "published": "Sat, 12 Jul 2025 02:25:23 +0000",
      "sentiment": 0.14444444444444446
    },
    {
      "title": "Son of El Chapo Pleads Guilty to Sweeping Drug Charges",
      "link": "https://www.nytimes.com/2025/07/11/us/politics/el-chapo-son-pleads-guilty.html",
      "published": "Fri, 11 Jul 2025 20:40:22 +0000",
      "sentiment": -0.5
    },
    {
      "title": "Trump Administration Begins Mass Layoffs at U.S. State Department",
      "link": "https://www.nytimes.com/2025/07/11/us/politics/trump-state-department-layoffs.html",
      "published": "Fri, 11 Jul 2025 21:19:11 +0000",
      "sentiment": 0.16
    },
    {
      "title": "Pam Bondi and FBI’s Dan Bongino Clash Over Handling of Epstein Case",
      "link": "https://www.nytimes.com/2025/07/11/us/politics/jeffrey-epstein-pam-bondi-dan-bongino-clash.html",
      "published": "Fri, 11 Jul 2025 21:01:36 +0000",
      "sentiment": -0.07083333333333333
    },
    {
      "title": "Can ‘Superman’ Fly Above Today’s Polarized Politics?",
      "link": "https://www.nytimes.com/2025/07/11/movies/superman-politics-backlash.html",
      "published": "Fri, 11 Jul 2025 18:48:28 +0000",
      "sentiment": 0.4
    },
    {
      "title": "Appeals Court Overturns Plea Deal in 9/11 Case",
      "link": "https://www.nytimes.com/2025/07/11/us/politics/appeals-court-overturns-9-11-plea-deal.html",
      "published": "Sat, 12 Jul 2025 05:46:12 +0000",
      "sentiment": 0.0
    },
    {
      "title": "Trump Says NATO Countries Will Buy Weapons to Give to Ukraine",
      "link": "https://www.nytimes.com/2025/07/11/world/europe/trump-nato-weapons-ukraine.html",
      "published": "Fri, 11 Jul 2025 19:04:37 +0000",
      "sentiment": 0.0
    },
    {
      "title": "Judge Signals She Will Protect Abrego Garcia From Hasty Second Deportation",
      "link": "https://www.nytimes.com/2025/07/11/us/politics/abrego-garcia-deportation-judge-protection-trump.html",
      "published": "Fri, 11 Jul 2025 17:45:19 +0000",
      "sentiment": 0.025000000000000005
    },
    {
      "title": "S.E.C. Accuses Prominent Georgia Republican of Running Ponzi Scheme",
      "link": "https://www.nytimes.com/2025/07/11/us/politics/brant-frost-first-liberty-ponzi-scheme.html",
      "published": "Fri, 11 Jul 2025 18:33:15 +0000",
      "sentiment": 0.2833333333333333
    },
    {
      "title": "Republicans Blame Canada for Wildfire Smoke ‘Suffocating’ the U.S.",
      "link": "https://www.nytimes.com/2025/07/11/world/canada/wildfire-smoke-manitoba-us-congress.html",
      "published": "Fri, 11 Jul 2025 18:22:44 +0000",
      "sentiment": -0.5
    },
    {
      "title": "Trump Visits Texas Flood Sites: ‘Hell of a Situation, Isn’t It?’",
      "link": "https://www.nytimes.com/2025/07/11/us/politics/trump-texas-flood-sites.html",
      "published": "Sat, 12 Jul 2025 00:25:44 +0000",
      "sentiment": 0.0
    },
    {
      "title": "How Netanyahu Prolonged the War in Gaza to Stay in Power",
      "link": "https://www.nytimes.com/2025/07/11/magazine/benjamin-netanyahu-gaza-war.html",
      "published": "Sat, 12 Jul 2025 03:31:56 +0000",
      "sentiment": -0.2
    },
    {
      "title": "Rubio and China’s Top Envoy Vie for Influence in Asia Over Trump’s Tariffs",
      "link": "https://www.nytimes.com/2025/07/11/us/politics/china-us-asia-tariffs.html",
      "published": "Fri, 11 Jul 2025 15:51:14 +0000",
      "sentiment": 0.35
    }
  ]
}