{
  "entries": [
    {
      "title": "New Hampshire federal judge blocks Trump’s ban on birthright citizenship, claiming ‘irreparable harm’",
      "link": "https://nypost.com/2025/07/10/us-news/federal-judge-in-new-hampshire-blocks-birthright-citizenship-ban-for-all-infants/",
      "published": "Thu, 10 Jul 2025 11:38:27 -0400",
      "sentiment": 0.13636363636363635
    },
    {
      "title": "Drowning deer saved from ocean by Florida lifeguards: ‘We save lives’",
      "link": "https://nypost.com/2025/07/10/us-news/deer-rescued-from-ocean-by-lifeguards-along-central-florida-coastline/",
      "published": "Thu, 10 Jul 2025 11:33:52 -0400",
      "sentiment": 0.05
    },
    {
      "title": "Dozens of troubled NYPD recruits finally forced to resign after faulty hiring standards",
      "link": "https://nypost.com/2025/07/10/us-news/dozens-of-troubled-nypd-recruits-finally-forced-to-resign-after-faulty-hiring-standards/",
      "published": "Thu, 10 Jul 2025 11:04:49 -0400",
      "sentiment": -0.34
    },
    {
      "title": "Marco Rubio meets Russia’s Sergei Lavrov days after Trump calls out ‘bulls–t‘ Vladimir Putin",
      "link": "https://nypost.com/2025/07/10/us-news/marco-rubio-meets-russias-sergei-lavrov-after-trump-calls-out-vladimir-putin/",
      "published": "Thu, 10 Jul 2025 11:01:21 -0400",
      "sentiment": -0.0625
    },
    {
      "title": "Florida tourist hotspot nearly becomes sanctuary city before ICE policy reversed",
      "link": "https://nypost.com/2025/07/10/us-news/florida-tourist-hotspot-nearly-becomes-sanctuary-city-before-ice-policy-reversed/",
      "published": "Thu, 10 Jul 2025 10:51:10 -0400",
      "sentiment": -0.016666666666666663
    },
    {
      "title": "Mysterious murder of paddleboarder in small Maine town sparks fear as killer remains on the loose",
      "link": "https://nypost.com/2025/07/10/us-news/mysterious-murder-of-paddleboarder-sparks-fear-discomfort-in-small-maine-town-as-killer-still-unknown/",
      "published": "Thu, 10 Jul 2025 10:46:30 -0400",
      "sentiment": -0.05384615384615383
    },
    {
      "title": "Child care costs are ‘major problem’ for most US adults, poll reveals",
      "link": "https://nypost.com/2025/07/10/us-news/child-care-costs-are-major-problem-for-most-us-adults-poll/",
      "published": "Thu, 10 Jul 2025 10:09:56 -0400",
      "sentiment": 0.10305555555555557
    },
    {
      "title": "Footage shows Texas floods cause $1.5M of damage to luxury cars in auto shop",
      "link": "https://nypost.com/2025/07/10/us-news/texas-floods-cause-1-5m-of-damage-to-luxury-cars-in-auto-shop-footage-shows/",
      "published": "Thu, 10 Jul 2025 10:07:06 -0400",
      "sentiment": 0.0
    },
    {
      "title": "Activist’s conviction for satirical Hillary Clinton memes tossed by appeals court: ‘Hallelujah!’",
      "link": "https://nypost.com/2025/07/10/us-news/activists-conviction-for-hillary-clinton-memes-tossed-by-appeals-courts/",
      "published": "Thu, 10 Jul 2025 10:00:51 -0400",
      "sentiment": -0.30000000000000004
    },
    {
      "title": "NYC woman reports Coney Island rape on July 4th — as onlookers laughed and recorded",
      "link": "https://nypost.com/2025/07/10/us-news/woman-says-she-was-raped-on-coney-island-and-witnesses-just-laughed-and-recorded/",
      "published": "Thu, 10 Jul 2025 09:21:32 -0400",
      "sentiment": 0.7
    },
    {
      "title": "Sicko says he beheaded his father on YouTube because dad wanted to stop him from becoming the next Donald Trump",
      "link": "https://nypost.com/2025/07/10/us-news/sicko-says-he-beheaded-his-father-on-youtube-because-dad-wanted-to-stop-him-from-becoming-the-next-donald-trump/",
      "published": "Thu, 10 Jul 2025 09:17:15 -0400",
      "sentiment": 0.225
    },
    {
      "title": "Steve Bannon calls for special prosecutor to investigate Jeffrey Epstein files",
      "link": "https://nypost.com/2025/07/10/us-news/steve-bannon-wants-special-probe-into-investigate-jeffrey-epstein-files/",
      "published": "Thu, 10 Jul 2025 08:22:15 -0400",
      "sentiment": 0.1380952380952381
    },
    {
      "title": "I was fed up with ‘toxic’ sunscreens so I started making my own with a ‘hero ingredient’ — now Oprah’s a fan",
      "link": "https://nypost.com/2025/07/10/health/my-nontoxic-sunscreens-hero-ingredient-gets-rid-of-white-cast/",
      "published": "Thu, 10 Jul 2025 08:00:00 -0400",
      "sentiment": 0.08888888888888889
    },
    {
      "title": "US Marshals call off hunt for ‘killer dad’ Travis Decker in Idaho after false-alarm sighting",
      "link": "https://nypost.com/2025/07/10/us-news/us-marshals-call-off-hunt-for-killer-dad-travis-decker-in-idaho-after-false-alarm-sighting/",
      "published": "Thu, 10 Jul 2025 07:55:33 -0400",
      "sentiment": 0.0
    },
    {
      "title": "NY paper’s ‘vile’ political cartoon appears to mock Trump-voting Texas flood victims",
      "link": "https://nypost.com/2025/07/10/us-news/ny-papers-vile-political-cartoon-draws-outrage-for-appearing-to-mock-trump-voting-texas-flood-victims/",
      "published": "Thu, 10 Jul 2025 07:44:30 -0400",
      "sentiment": -0.1
    },
    {
      "title": "Fired doctor grovels after her foul post suggesting flood victims were Trump supporters who got ‘what they voted for’ sparked outrage",
      "link": "https://nypost.com/2025/07/10/us-news/houston-pediatrician-speaks-out-after-her-flood-victims-post-sparked-outrage/",
      "published": "Thu, 10 Jul 2025 07:33:02 -0400",
      "sentiment": 0.0
    },
    {
      "title": "Violent MS-13 kingpin wanted for five murders and another gang member arrested by ICE in Omaha",
      "link": "https://nypost.com/2025/07/10/us-news/violent-ms-13-kingpin-wanted-for-five-murders-and-another-gang-member-arrested-by-ice-in-omaha/",
      "published": "Thu, 10 Jul 2025 07:13:12 -0400",
      "sentiment": 0.06666666666666665
    },
    {
      "title": "Jeffrey Epstein’s chilling final message before his death revealed",
      "link": "https://nypost.com/2025/07/10/us-news/jeffrey-epstein-sent-eerie-final-message-hours-before-suicide-michael-wolff/",
      "published": "Thu, 10 Jul 2025 06:46:48 -0400",
      "sentiment": -0.19999999999999998
    },
    {
      "title": "Zohran Mamdani’s feeding off Gen Z’s misplaced doomerism: ‘They perpetually think things are awful’",
      "link": "https://nypost.com/2025/07/10/us-news/zohran-mamdanis-feeding-off-gen-zs-misplaced-doomerism/",
      "published": "Thu, 10 Jul 2025 06:00:00 -0400",
      "sentiment": -0.17857142857142858
    },
    {
      "title": "NYC Jewish pols urged to join ‘Jews for Zohran’ Mamdani and back Israel-bashing nominee for mayor",
      "link": "https://nypost.com/2025/07/10/us-news/nyc-jewish-pols-urged-to-join-jews-for-zohran-mamdani-and-back-israel-bashing-nominee-for-mayor/",
      "published": "Thu, 10 Jul 2025 06:00:00 -0400",
      "sentiment": 0.21666666666666667
    }
  ]
}